pdf_annotate/__init__.py
pdf_annotate/annotator.py
pdf_annotate/graphics.py
pdf_annotate/annotations/__init__.py
pdf_annotate/annotations/base.py
pdf_annotate/annotations/image.py
pdf_annotate/annotations/points.py
pdf_annotate/annotations/rect.py
pdf_annotate/annotations/text.py
pdf_annotate/config/__init__.py
pdf_annotate/config/appearance.py
pdf_annotate/config/constants.py
pdf_annotate/config/graphics_state.py
pdf_annotate/config/location.py
pdf_annotate/config/metadata.py
pdf_annotate/fonts/Helvetica.ttf
pdf_annotate/util/__init__.py
pdf_annotate/util/font_metrics.py
pdf_annotate/util/geometry.py
pdf_annotate/util/text.py
pdf_annotate/util/true_type_font.py
pdf_annotate/util/validation.py
pdf_annotate-0.12.0.dist-info/LICENSE
pdf_annotate-0.12.0.dist-info/METADATA
pdf_annotate-0.12.0.dist-info/WHEEL
pdf_annotate-0.12.0.dist-info/top_level.txt
pdf_annotate-0.12.0.dist-info/RECORD
