Metadata-Version: 2.1
Name: pdf-annotate
Version: 0.12.0
Summary: Add annotations to PDFs
Home-page: https://github.com/plangrid/pdf-annotate
Author: Michael Bryant
Author-email: smart-recordset@plangrid.com
License: UNKNOWN
Platform: UNKNOWN
Classifier: Programming Language :: Python :: 3
Classifier: License :: OSI Approved :: MIT License
Classifier: Operating System :: OS Independent
Provides-Extra: tests
